{
  "auctionId": "a15a4fb6-f9ce-4b09-a0cc-0672f1de4d20",
  "correlationId": "zGg2TfRsBNbqlc7AVdhLAw",
  "placements": {
    "mraid": "UX-47c9ac4c-39c5-4e0e-685e-52d4619dcb85"
  },
  "media": {
    "UX-47c9ac4c-39c5-4e0e-685e-52d4619dcb85": {
      "adType": "mraid-sample-ad-type",
      "creativeId": "mraid-sample-creative-id",
      "seatId": 902,
      "contentType": "programmatic/mraid",
      "content": null,
      "trackingUrls": {
        "impression": [
          "https://ads-brand-postback.unityads.unity3d.com/brands/2000/%ZONE%/impression/common?data=Kz2J"
        ]
      }
    }
  }
}
